simplesitesearch/__init__.py
simplesitesearch/cms_apps.py
simplesitesearch/urls.py
simplesitesearch/views.py
simplesitesearch/templates/simplesitesearch/pagination.html
simplesitesearch/templates/simplesitesearch/search_results.html
simplesitesearch-1.0.4.dist-info/licenses/LICENSE
simplesitesearch-1.0.4.dist-info/METADATA
simplesitesearch-1.0.4.dist-info/WHEEL
simplesitesearch-1.0.4.dist-info/top_level.txt
simplesitesearch-1.0.4.dist-info/RECORD
