Metadata-Version: 2.4
Name: simplesitesearch
Version: 1.0.4
Summary: Reptile Simple Site Search django app
Home-page: https://github.com/reptiletech/simplesitesearch
Author: Reptile Tech
Author-email: Reptile Tech <flouis@reptile.tech>
Maintainer-email: Reptile Tech <flouis@reptile.tech>
License: MIT
Project-URL: Homepage, https://github.com/reptiletech/simplesitesearch
Project-URL: Documentation, https://github.com/reptiletech/simplesitesearch#readme
Project-URL: Repository, https://github.com/reptiletech/simplesitesearch.git
Project-URL: Bug Tracker, https://github.com/reptiletech/simplesitesearch/issues
Keywords: django,search,cms,django-cms
Classifier: Development Status :: 5 - Production/Stable
Classifier: Intended Audience :: Developers
Classifier: License :: OSI Approved :: MIT License
Classifier: Operating System :: OS Independent
Classifier: Programming Language :: Python :: 3
Classifier: Programming Language :: Python :: 3.6
Classifier: Programming Language :: Python :: 3.7
Classifier: Programming Language :: Python :: 3.8
Classifier: Programming Language :: Python :: 3.9
Classifier: Programming Language :: Python :: 3.10
Classifier: Programming Language :: Python :: 3.11
Classifier: Programming Language :: Python :: 3.12
Classifier: Framework :: Django
Classifier: Framework :: Django :: 2.2
Classifier: Framework :: Django :: 3.2
Classifier: Framework :: Django :: 4.0
Classifier: Framework :: Django :: 4.1
Classifier: Framework :: Django :: 4.2
Classifier: Framework :: Django :: 5.0
Classifier: Topic :: Internet :: WWW/HTTP :: Dynamic Content
Classifier: Topic :: Software Development :: Libraries :: Python Modules
Requires-Python: >=3.6
License-File: LICENSE
Requires-Dist: Django>=2.2
Requires-Dist: django-cms>=3.2
Requires-Dist: requests>=2.25.0
Dynamic: author
Dynamic: home-page
Dynamic: license-file
Dynamic: requires-python
